[{"title":"A Wizard of Earthsea\n","link":"/wiki/A_Wizard_of_Earthsea","year":"1968"},{"title":"The Tombs of Atuan\n","link":"/wiki/The_Tombs_of_Atuan","year":"1971"},{"title":"The Farthest Shore\n","link":"/wiki/The_Farthest_Shore","year":"1972"},{"title":"Tehanu\n","link":"/wiki/Tehanu","year":"1990"},{},{"title":"The Other Wind\n","link":"/wiki/The_Other_Wind","year":"2001"},{},{},{},{},{},{},{},{"title":"Rocannon's World\n","link":"/wiki/Rocannon%27s_World","year":"1966"},{"title":"Planet of Exile\n","link":"/wiki/Planet_of_Exile","year":"1966"},{"title":"City of Illusions\n","link":"/wiki/City_of_Illusions","year":"1967"},{"title":"The Left Hand of Darkness\n","link":"/wiki/The_Left_Hand_of_Darkness","year":"1969"},{"title":"The Dispossessed\n","link":"/wiki/The_Dispossessed","year":"1974"},{"title":"\"The Word for World Is Forest\"\n","link":"/wiki/The_Word_for_World_Is_Forest","year":"1972"},{},{"title":"The Telling\n","link":"/wiki/The_Telling","year":"2000"},{},{},{},{},{},{},{},{},{},{},{},{},{},{},{},{},{},{},{},{},{},{},{},{},{"title":"Malafrena\n","link":"/wiki/Malafrena","year":"1979"},{},{},{"title":"Gifts\n","link":"/wiki/Gifts_(novel)","year":"2004"},{"title":"Voices\n","link":"/wiki/Voices_(Le_Guin_novel)","year":"2006"},{"title":"Powers\n","link":"/wiki/Powers_(novel)","year":"2007"},{},{},{},{},{"title":"Always Coming Home\n","link":"/wiki/Always_Coming_Home","year":"1985"},{},{},{},{"title":"The Lathe of Heaven\n","link":"/wiki/The_Lathe_of_Heaven","year":"1971"},{"title":"Very Far Away from Anywhere Else\n","year":"1976"},{"title":"The Eye of the Heron\n","link":"/wiki/The_Eye_of_the_Heron","year":"1978"},{"title":"The Beginning Place\n","link":"/wiki/The_Beginning_Place","year":"1980"},{"title":"Lavinia\n","link":"/wiki/Lavinia_(novel)","year":"2008"},{},{},{},{},{},{},{},{},{},{},{},{},{},{"title":"\"Nine Lives\"\n","link":"/wiki/Nine_Lives_(novelette)","year":"1969"},{},{},{},{},{},{},{},{},{},{},{},{},{},{},{},{},{},{},{},{},{},{},{},{},{},{},{},{},{},{},{},{},{},{},{},{},{},{},{},{},{},{},{},{},{},{},{},{},{},{},{},{},{},{},{},{},{},{},{},{},{},{},{},{},{},{},{},{},{},{},{},{},{},{},{},{},{},{},{},{},{},{},{},{},{},{},{},{},{},{},{}]
